safe_pfl_plotter/__init__.py
safe_pfl_plotter/logs_plotter.py
safe_pfl_plotter-0.1.2.dist-info/LICENSE
safe_pfl_plotter-0.1.2.dist-info/METADATA
safe_pfl_plotter-0.1.2.dist-info/WHEEL
safe_pfl_plotter-0.1.2.dist-info/top_level.txt
safe_pfl_plotter-0.1.2.dist-info/RECORD
